json3/__init__.py
json3-1.0.dist-info/METADATA
json3-1.0.dist-info/WHEEL
json3-1.0.dist-info/top_level.txt
json3-1.0.dist-info/RECORD
