Metadata-Version: 2.1
Name: json3
Version: 1.0
Summary: All in `json3.Json.__docs__`.
Author: wer310Libs
License: UNKNOWN
Platform: UNKNOWN
Classifier: Programming Language :: Python :: 3
